nodevectors/__init__.py
nodevectors/embedders.py
nodevectors/ggvec.py
nodevectors/glove.py
nodevectors/grarep.py
nodevectors/node2vec.py
nodevectors/prone.py
nodevectors/evaluation/__init__.py
nodevectors/evaluation/graph_eval.py
nodevectors/evaluation/link_pred.py
nodevectors-0.2.0.dist-info/METADATA
nodevectors-0.2.0.dist-info/WHEEL
nodevectors-0.2.0.dist-info/top_level.txt
nodevectors-0.2.0.dist-info/RECORD
