Metadata-Version: 2.1
Name: nodevectors
Version: 0.2.0
Summary: Fast network node embeddings
Home-page: https://github.com/VHRanger/nodevectors/
Author: Matt Ranger
Author-email: Matt Ranger <matt@singlelunch.com>
License: MIT License
Project-URL: Home Page, https://github.com/VHRanger/nodevectors/
Project-URL: github, https://github.com/VHRanger/nodevectors/
Keywords: graph,network,embedding,node2vec
Requires-Python: >=3.12
Requires-Dist: csrgraph
Requires-Dist: gensim
Requires-Dist: networkx==2.5.1
Requires-Dist: numba
Requires-Dist: numpy
Requires-Dist: pandas>=1.0
Requires-Dist: scipy
Requires-Dist: scikit-learn
